tagr/__init__.py
tagr/config.py
tagr/utils.py
tagr/storage/__init__.py
tagr/storage/aws.py
tagr/storage/aws_helper.py
tagr/storage/azure.py
tagr/storage/gcp.py
tagr/storage/local.py
tagr/tagging/__init__.py
tagr/tagging/artifacts.py
tagr-0.0.1.dist-info/LICENSE
tagr-0.0.1.dist-info/METADATA
tagr-0.0.1.dist-info/WHEEL
tagr-0.0.1.dist-info/top_level.txt
tagr-0.0.1.dist-info/RECORD
