Metadata-Version: 2.1
Name: tagr
Version: 0.0.1
Summary: UNKNOWN
Home-page: https://github.com/tagr-dev/tagr
Author: Sunrise Long
Author-email: sunrise.long@yahoo.ca
License: MIT
Platform: UNKNOWN
Classifier: Programming Language :: Python :: 3
Classifier: License :: OSI Approved :: MIT License
Classifier: Operating System :: OS Independent
License-File: LICENSE
Requires-Dist: numpy
Requires-Dist: pandas
Requires-Dist: boto3
Requires-Dist: azure-storage-blob
Requires-Dist: google-cloud-storage
